{
    "Exercises": {
        "Compound": {
            "Overhead Press": {
                "Equipment": ["Barbell"],
                "MuscleGroups": {
                    "frontdelts": 1.0,
                    "sideDelts": 0.3,
                    "triceps": 0.5
                }
            },
            "Seated Dumbbell Press": {
                "Equipment": ["Dumbbell"],
                "MuscleGroups": {
                    "frontdelts": 1.0,
                    "sideDelts": 0.3,
                    "triceps": 0.4
                }
            },
            "Seated Barbell Press": {
                "Equipment": ["Barbell", "Bench"],
                "MuscleGroups": {
                    "frontdelts": 1.0,
                    "sideDelts": 0.3,
                    "triceps": 0.5
                }
            },
            "Machine Shoulder Press": {
                "Equipment": ["Machine"],
                "MuscleGroups": {
                    "frontdelts": 1.0,
                    "sideDelts": 0.3,
                    "triceps": 0.5
                }
            }
        },
        "Isolation": {
            "Front Raise (Dumbbell)": {
                "Equipment": ["Dumbbell"],
                "MuscleGroups": {
                    "frontdelts": 1.0,
                    "sideDelts": 0.4,
                    "upperchest": 0.3
                }
            },
            "Cable Front Raise": {
                "Equipment": ["Cable Machine"],
                "MuscleGroups": {
                    "frontdelts": 1.0,
                    "sideDelts": 0.3
                }
            }
        }
    }
}
